{
  "_class": "group",
  "booleanOperation": 0,
  "do_objectID": "625D2C61-F746-49F0-81BD-B7C4AE940D40",
  "exportOptions": {
    "_class": "exportOptions",
    "do_objectID": "83786588-84D9-4B50-9C16-F339E5746633",
    "exportFormats": [
    ],
    "includedLayerIds": [
    ],
    "layerOptions": 0,
    "shouldTrim": false
  },
  "frame": {
    "_class": "rect",
    "constrainProportions": false,
    "do_objectID": "44A5CD08-37D5-42DB-9331-2A818CF8D87E",
    "height": 31,
    "width": 82,
    "x": 357,
    "y": 0
  },
  "hasClickThrough": false,
  "isFixedToViewport": false,
  "isFlippedHorizontal": false,
  "isFlippedVertical": false,
  "isLocked": false,
  "isVisible": true,
  "layerListExpandedType": 0,
  "layers": [
    {
      "class": "text",
      "id": "E8B455D1-3E7F-4B73-9195-848D968B864E"
    },
    {
      "class": "text",
      "id": "978D67B3-E7B6-497B-A45A-DA62C7360A84"
    }
  ],
  "name": "Group 2",
  "nameIsFixed": false,
  "resizingConstraint": 63,
  "resizingType": 0,
  "rotation": 0,
  "shouldBreakMaskChain": false,
  "style": {
    "_class": "style",
    "do_objectID": "1F091E93-75D6-4E4D-8FCB-C09E68387295",
    "endMarkerType": 0,
    "miterLimit": 10,
    "startMarkerType": 0,
    "windingRule": 1
  },
  "userInfo": {
    "com.animaapp.stc-sketch-plugin": {
      "kModelPropertiesKey": {
      }
    }
  }
}